drt_mask_generator/__init__.py
drt_mask_generator/app.py
drt_mask_generator/form.ui
drt_mask_generator-0.0.8.dist-info/LICENSE
drt_mask_generator-0.0.8.dist-info/METADATA
drt_mask_generator-0.0.8.dist-info/WHEEL
drt_mask_generator-0.0.8.dist-info/top_level.txt
drt_mask_generator-0.0.8.dist-info/RECORD
